RiskQuantLib/__init__.py
RiskQuantLib/module.py
RiskQuantLib/Auto/__init__.py
RiskQuantLib/Auto/Instrument/__init__.py
RiskQuantLib/Auto/Instrument/instrument.py
RiskQuantLib/Auto/InstrumentList/__init__.py
RiskQuantLib/Auto/InstrumentList/instrumentList.py
RiskQuantLib/Build/__init__.py
RiskQuantLib/Build/builder.py
RiskQuantLib/Build/controller.py
RiskQuantLib/Build/debugger.py
RiskQuantLib/Build/render.py
RiskQuantLib/Build/router.py
RiskQuantLib/Build/tree.py
RiskQuantLib/Build/Component/__init__.py
RiskQuantLib/Build/Component/macro.pyt
RiskQuantLib/Build/Component/ContentGenerator/__init__.py
RiskQuantLib/Build/Component/ContentGenerator/filePath.pyt
RiskQuantLib/Build/Component/ContentGenerator/module.pyt
RiskQuantLib/Build/Component/ContentGenerator/setAttribute.pyt
RiskQuantLib/Build/Component/ContentGenerator/setAttributeList.pyt
RiskQuantLib/Build/Component/ContentGenerator/sourceCodeDebugger.pyt
RiskQuantLib/Build/Component/FileInitiator/__init__.py
RiskQuantLib/Build/Component/FileInitiator/instrument.pyt
RiskQuantLib/Build/Component/FileInitiator/instrumentAuto.pyt
RiskQuantLib/Build/Component/FileInitiator/instrumentList.pyt
RiskQuantLib/Build/Component/FileInitiator/instrumentListAuto.pyt
RiskQuantLib/Build/Component/FileInitiator/property.pyt
RiskQuantLib/Instrument/__init__.py
RiskQuantLib/Instrument/instrument.py
RiskQuantLib/InstrumentList/__init__.py
RiskQuantLib/InstrumentList/instrumentList.py
RiskQuantLib/Model/__init__.py
RiskQuantLib/Model/model.py
RiskQuantLib/Model/Copula/__init__.py
RiskQuantLib/Model/Copula/copula.py
RiskQuantLib/Model/KMV/__init__.py
RiskQuantLib/Model/KMV/kmv.py
RiskQuantLib/Operation/__init__.py
RiskQuantLib/Operation/operation.py
RiskQuantLib/Operation/vectorization.py
RiskQuantLib/Property/__init__.py
RiskQuantLib/Property/property.py
RiskQuantLib/Tool/__init__.py
RiskQuantLib/Tool/codeTool.py
RiskQuantLib/Tool/databaseTool.py
RiskQuantLib/Tool/dateTool.py
RiskQuantLib/Tool/decoratorTool.py
riskquantlib-0.4.3.dist-info/licenses/LICENSE
riskquantlib-0.4.3.dist-info/METADATA
riskquantlib-0.4.3.dist-info/WHEEL
riskquantlib-0.4.3.dist-info/entry_points.txt
riskquantlib-0.4.3.dist-info/top_level.txt
riskquantlib-0.4.3.dist-info/RECORD
