Metadata-Version: 2.4
Name: RiskQuantLib
Version: 0.4.3
Summary: RiskQuantLib is a QuantLib derivative to evaluate risk.
Author-email: Syuya_Murakami <SyuyaMurakami@icloud.com>
License-Expression: MIT
Project-URL: Homepage, https://riskquantlib-doc.readthedocs.io/en/latest/index.html
Project-URL: Bug Tracker, https://github.com/SyuyaMurakami/RiskQuantLib
Classifier: Programming Language :: Python :: 3
Classifier: Operating System :: OS Independent
Requires-Python: >=3.8
License-File: LICENSE
Requires-Dist: numpy
Requires-Dist: pandas
Requires-Dist: QuantLib
Dynamic: license-file
